sweecrypt/__init__.py
sweecrypt/cli.py
sweecrypt-1.1.4.dist-info/licenses/LICENSE
sweecrypt-1.1.4.dist-info/METADATA
sweecrypt-1.1.4.dist-info/WHEEL
sweecrypt-1.1.4.dist-info/entry_points.txt
sweecrypt-1.1.4.dist-info/top_level.txt
sweecrypt-1.1.4.dist-info/RECORD
