Metadata-Version: 2.4
Name: sweecrypt
Version: 1.1.4
Summary: An easy and fun encryption module.
Author-email: Swee <meow@swee.codes>
License: MIT
Project-URL: Homepage, https://swee.codes/apps/sweecrypt
Project-URL: Repository, https://git.swee.codes/SweeZero/SweeCrypt
Project-URL: Issues, https://git.swee.codes/SweeZero/SweeCrypt/issues
Project-URL: Changelog, https://git.swee.codes/SweeZero/SweeCrypt/releases
Classifier: Programming Language :: Python :: 3
Classifier: Operating System :: OS Independent
Requires-Python: >=3.9
License-File: LICENSE
Requires-Dist: typer
Requires-Dist: typing-extensions
Dynamic: license-file
